{
  "meta": {
    "region": "San Antonio",
    "state": "Texas",
    "abbr": "TX",
    "city": "sanantonio",
    "postal": "78205",
    "scraped_at": "2026-07-02T14:52:31.086Z",
    "input_urls": 2,
    "kept": 2,
    "skipped_no_images": 0,
    "skipped_errors": 0
  },
  "listings": [
    {
      "craigslist": {
        "url": "https://www.craigslist.org/view/d/san-antonio-tailored-for-pet-lovers-bed/fSLdUifh9YEQer2WzjonK6",
        "posting_id": "7944691682",
        "title": "Tailored for pet lovers! 2 Bed/2 Bath in our pet-friendly community.",
        "price": 1239,
        "price_text": "$1,239",
        "room": 2,
        "area": "1006",
        "loft": "1",
        "location": "2003 Oakhill Dr",
        "full_address": "2003 Oakhill Dr, San Antonio Tailored",
        "locality": "San Antonio Tailored",
        "geocode_query": "2003 Oakhill Dr, San Antonio Tailored",
        "description": "QR Code Link to This Post Welcome to Vivid Apartment Homes! 2003 Oakhill Dr San Antonio, TX 78238 Call us today! show contact info Rental Size: 2 BR - 2 BA - 1006 sq ft Monthly Price: $1239 *Optional and usage-based charges not included. Contact office to confirm pricing details and included fees. Lease Length: 6-Month, 12-Month Our one- and two-bedroom apartments are available in both renovated and classic styles. Renovated homes feature updated vinyl flooring, matte black fixtures, and modern finishes, while every apartment includes a fully equipped kitchen, granite-inspired countertops, and a private patio or balcony. Enjoy community amenities like our sparkling pool, fitness center, dog park, outdoor lounge, and on-site laundromat. Plus, exciting upgrades are coming soon. Our community features: ❖ Barbecue and Grilling Area ❖ Clubhouse ❖ Laundry Facility ❖ Off-street Parking ❖ Outdoor Lounge Area ❖ Pet-Friendly ❖ Bark Park ❖ Fitness Center ❖ Paid Lawn Care ❖ Sundeck ❖ Swimming Pool Our apartment features: ❖ Black Appliances ❖ Ceiling Fans in Select Units ❖ Fully-equipped Kitchen ❖ Personal Balcony or Patio ❖ Extra Storage Space ❖ Granite-inspired Countertops ❖ Tile Kitchen Backsplash ❖ Wood-inspired Flooring in Select Units Call us today! -- show contact info -- Our Pet-Policy: Pets Welcome Upon Approval. No breed, weight, or size restrictions. Limit of 2 pets per home. Non-refundable pet fee is $300. Monthly pet rent of $20 will be charged per pet. Rabies shot must be provided. Large aquariums will require additional proof of insurance. Please call office for details. Pet Amenities: Bark Park Website: www.rentalsapts.com?n=vivid&rp=fSLdUifh9YEQ&t=wb Online Application: www.rentalsapts.com?n=vivid&rp=fSLdUifh9YEQ&t=ap Schedule a Tour: www.rentalsapts.com?n=vivid&rp=fSLdUifh9YEQ&t=sch All pricing, availability, fees, and terms are subject to change without notice. EQUAL HOUSING OPPORTUNITY 7L2ZZ5J7SVJN0OH",
        "phone": "",
        "image_urls": [
          "https://images.craigslist.org/01414_atBKfJ1YtVu_0uY0kE_600x450.jpg",
          "https://images.craigslist.org/00T0T_5Z1OqckmSPc_0vm0l2_600x450.jpg",
          "https://images.craigslist.org/00g0g_8lWoFlbcQGS_0uY0kE_600x450.jpg",
          "https://images.craigslist.org/00Z0Z_JQvulZQ9vI_0uY0kE_600x450.jpg",
          "https://images.craigslist.org/00Y0Y_656XHJM8jfm_0uY0kE_600x450.jpg",
          "https://images.craigslist.org/00P0P_gBMgxmvSAc2_0oc0g8_600x450.jpg",
          "https://images.craigslist.org/00I0I_5AELQa2NIJv_0uY0kE_600x450.jpg",
          "https://images.craigslist.org/00Q0Q_l6FVeTkWObh_0uY0kE_600x450.jpg",
          "https://images.craigslist.org/01111_8GWweuJHTjG_0uY0kE_600x450.jpg",
          "https://images.craigslist.org/00V0V_1eY5sZiCEjf_0uY0kE_600x450.jpg",
          "https://images.craigslist.org/00J0J_kLlajyairw4_0uY0kE_600x450.jpg",
          "https://images.craigslist.org/01111_hEsoLjGuLTU_0uY0kE_600x450.jpg",
          "https://images.craigslist.org/00u0u_aUyE1BGXu59_0uY0kE_600x450.jpg",
          "https://images.craigslist.org/00Z0Z_1c8RunF19sT_0uY0kE_600x450.jpg",
          "https://images.craigslist.org/00w0w_3Xq0oTr3SyM_0uY0kE_600x450.jpg",
          "https://images.craigslist.org/00a0a_gaaZyfPXYYB_0uY0kE_600x450.jpg",
          "https://images.craigslist.org/01717_cznnYV5z57O_0uY0kE_600x450.jpg",
          "https://images.craigslist.org/00r0r_4t1njqriMZi_0uY0kE_600x450.jpg",
          "https://images.craigslist.org/00I0I_dYbYEpU3q7U_0uY0kE_600x450.jpg",
          "https://images.craigslist.org/00i0i_l8oDhL7WRms_0uY0kE_600x450.jpg",
          "https://images.craigslist.org/01515_dGzS5M8uTWk_0uY0kE_600x450.jpg",
          "https://images.craigslist.org/00j0j_3gR9lTj58Zv_0uY0kE_600x450.jpg",
          "https://images.craigslist.org/00p0p_6o1bzFw8mXC_0uY0kE_600x450.jpg",
          "https://images.craigslist.org/00W0W_1eN4oLgf0gr_0uY0uY_600x450.jpg",
          "https://images.craigslist.org/01414_atBKfJ1YtVu_0uY0kE_1200x900.jpg",
          "https://images.craigslist.org/00T0T_5Z1OqckmSPc_0vm0l2_1200x900.jpg",
          "https://images.craigslist.org/00g0g_8lWoFlbcQGS_0uY0kE_1200x900.jpg",
          "https://images.craigslist.org/00Z0Z_JQvulZQ9vI_0uY0kE_1200x900.jpg",
          "https://images.craigslist.org/00Y0Y_656XHJM8jfm_0uY0kE_1200x900.jpg",
          "https://images.craigslist.org/00P0P_gBMgxmvSAc2_0oc0g8_1200x900.jpg",
          "https://images.craigslist.org/00I0I_5AELQa2NIJv_0uY0kE_1200x900.jpg",
          "https://images.craigslist.org/00Q0Q_l6FVeTkWObh_0uY0kE_1200x900.jpg",
          "https://images.craigslist.org/01111_8GWweuJHTjG_0uY0kE_1200x900.jpg",
          "https://images.craigslist.org/00V0V_1eY5sZiCEjf_0uY0kE_1200x900.jpg",
          "https://images.craigslist.org/00J0J_kLlajyairw4_0uY0kE_1200x900.jpg",
          "https://images.craigslist.org/01111_hEsoLjGuLTU_0uY0kE_1200x900.jpg",
          "https://images.craigslist.org/00u0u_aUyE1BGXu59_0uY0kE_1200x900.jpg",
          "https://images.craigslist.org/00Z0Z_1c8RunF19sT_0uY0kE_1200x900.jpg",
          "https://images.craigslist.org/00w0w_3Xq0oTr3SyM_0uY0kE_1200x900.jpg",
          "https://images.craigslist.org/00a0a_gaaZyfPXYYB_0uY0kE_1200x900.jpg",
          "https://images.craigslist.org/01717_cznnYV5z57O_0uY0kE_1200x900.jpg",
          "https://images.craigslist.org/00r0r_4t1njqriMZi_0uY0kE_1200x900.jpg",
          "https://images.craigslist.org/00I0I_dYbYEpU3q7U_0uY0kE_1200x900.jpg",
          "https://images.craigslist.org/00i0i_l8oDhL7WRms_0uY0kE_1200x900.jpg",
          "https://images.craigslist.org/01515_dGzS5M8uTWk_0uY0kE_1200x900.jpg",
          "https://images.craigslist.org/00j0j_3gR9lTj58Zv_0uY0kE_1200x900.jpg",
          "https://images.craigslist.org/00p0p_6o1bzFw8mXC_0uY0kE_1200x900.jpg",
          "https://images.craigslist.org/00W0W_1eN4oLgf0gr_0uY0uY_1200x900.jpg",
          "https://images.craigslist.org/01414_atBKfJ1YtVu_0uY0kE_50x50c.jpg",
          "https://images.craigslist.org/00T0T_5Z1OqckmSPc_0vm0l2_50x50c.jpg",
          "https://images.craigslist.org/00g0g_8lWoFlbcQGS_0uY0kE_50x50c.jpg",
          "https://images.craigslist.org/00Z0Z_JQvulZQ9vI_0uY0kE_50x50c.jpg",
          "https://images.craigslist.org/00Y0Y_656XHJM8jfm_0uY0kE_50x50c.jpg",
          "https://images.craigslist.org/00P0P_gBMgxmvSAc2_0oc0g8_50x50c.jpg",
          "https://images.craigslist.org/00I0I_5AELQa2NIJv_0uY0kE_50x50c.jpg",
          "https://images.craigslist.org/00Q0Q_l6FVeTkWObh_0uY0kE_50x50c.jpg",
          "https://images.craigslist.org/01111_8GWweuJHTjG_0uY0kE_50x50c.jpg",
          "https://images.craigslist.org/00V0V_1eY5sZiCEjf_0uY0kE_50x50c.jpg",
          "https://images.craigslist.org/00J0J_kLlajyairw4_0uY0kE_50x50c.jpg",
          "https://images.craigslist.org/01111_hEsoLjGuLTU_0uY0kE_50x50c.jpg",
          "https://images.craigslist.org/00u0u_aUyE1BGXu59_0uY0kE_50x50c.jpg",
          "https://images.craigslist.org/00Z0Z_1c8RunF19sT_0uY0kE_50x50c.jpg",
          "https://images.craigslist.org/00w0w_3Xq0oTr3SyM_0uY0kE_50x50c.jpg",
          "https://images.craigslist.org/00a0a_gaaZyfPXYYB_0uY0kE_50x50c.jpg",
          "https://images.craigslist.org/01717_cznnYV5z57O_0uY0kE_50x50c.jpg",
          "https://images.craigslist.org/00r0r_4t1njqriMZi_0uY0kE_50x50c.jpg",
          "https://images.craigslist.org/00I0I_dYbYEpU3q7U_0uY0kE_50x50c.jpg",
          "https://images.craigslist.org/00i0i_l8oDhL7WRms_0uY0kE_50x50c.jpg",
          "https://images.craigslist.org/01515_dGzS5M8uTWk_0uY0kE_50x50c.jpg",
          "https://images.craigslist.org/00j0j_3gR9lTj58Zv_0uY0kE_50x50c.jpg",
          "https://images.craigslist.org/00p0p_6o1bzFw8mXC_0uY0kE_50x50c.jpg",
          "https://images.craigslist.org/00W0W_1eN4oLgf0gr_0uY0uY_50x50c.jpg"
        ],
        "housing_type": "house",
        "baths": 2,
        "image_files": [
          "27d7153dc642fe53686aea49450c2808.jpg",
          "097324a14c21aab3907f9bca0da96221.jpg",
          "bdef2a67bd079e32ec21de4900ea94dc.jpg",
          "1ef90e06e461c1e3592f60dbd3309b14.jpg",
          "73ccb4828d7d5a23ff07916b0c5bb20f.jpg",
          "daa5ab8b0265f59ee4c8be938d4b57bf.jpg",
          "4b780514a50582d660ba4c95c311f097.jpg",
          "6db2e537d0f6d4b1c8945ae6ea3bd9e8.jpg",
          "38b9fbf90609de7259760c28869e027e.jpg",
          "8c73c9dd6f4ce5dfc15c55052c3acea1.jpg",
          "947fb8e1c12fa6d80b1a237d7236724c.jpg",
          "97d330d127752fb4d4117c842e9e1a4f.jpg",
          "74aa2d68b958a333606b459a07b2a2d8.jpg",
          "256b81dabf8fe3e1ccd66575bba6b95f.jpg",
          "10972997cb2817a47672c27a90a73a66.jpg",
          "910b295992f297c2edb146bd00a4de8c.jpg",
          "325d8cfa2f4edbba40e8b1061f82abd3.jpg",
          "e4027574fbc9973f1de64f057f7d3429.jpg",
          "02ae9db90cd861378842680a898e2aad.jpg",
          "b198c9800ff286d1e5418f39bae78bbd.jpg",
          "62c55c71195f9c2d7b8e340bb2c6a63a.jpg",
          "46a8d438e06c753e3a47ed81fe4f644b.jpg",
          "3134db0e8bf98743c890ff0ec15c9c64.jpg",
          "6e96b14a331747d0d9c1382c0cb1367b.jpg",
          "81c47e97d3dd2c44ca58f75e1dc64826.jpg",
          "074533de7478fdf56c4a66d6d2f371d0.jpg",
          "2e333db7c5c1ca0c2fef8f49e24e6af3.jpg",
          "3cf50f8b693f38a937a4b77de7e2b7dc.jpg",
          "7d40e529547fb5be09ee17041a985332.jpg",
          "3e83df866bcda276f5b635f75d6e7b6c.jpg",
          "60a4a3c366d74d0d9cc808a0b4a3d511.jpg",
          "9f3f6d753752539ad33998cb02d860d1.jpg",
          "bb2c3d93167fa46b34239c55329e41dd.jpg",
          "5a3c7c0c05f74bc566ea576b6d25fe89.jpg",
          "29a324050b244838cd38051a10c103bc.jpg",
          "2949602723cf5311f2f76093b87f4acf.jpg",
          "83e5f1e45eebc7dd915bb060f1a237b1.jpg",
          "6970e3c9a2646bac53db2c851371b1a5.jpg",
          "3cb6d6ceb055f0c6e9cb9be26747bef4.jpg",
          "ff0c324846e120e45b72fab09ba434f0.jpg",
          "631e40cfcc510159f735203811ebb159.jpg",
          "4bef90193c34b988e62ce43360fdcfac.jpg",
          "caaea9b520f541dbca068ac280cef8cb.jpg",
          "7a8f65666af75d3fad1282563fb0d38a.jpg",
          "cae6c2f7173ec9be81db2ba3dce0bb0a.jpg",
          "68a443703965c17669245e23eba3d7b7.jpg",
          "533aff44266c87ea003eef16356b802b.jpg",
          "624f9faa7e7f4671b73d7dc03c014aa7.jpg",
          "84088c89c9e309d6fb35274bf00662ea.jpg"
        ],
        "mainpic": "d958f140-52bf-4057-a923-624f49a60a20",
        "geo": {
          "street": "2003 Oakhill Dr",
          "display_state": "Texas",
          "display_city": "San Antonio Tailored County",
          "display_district": "San Antonio Tailored",
          "display_name": "2003 Oakhill Dr, San Antonio Tailored, TX",
          "lat": null,
          "lon": null,
          "address_json": {
            "source": "craigslist",
            "display_name": "2003 Oakhill Dr, San Antonio Tailored, TX",
            "address": {
              "road": "2003 Oakhill Dr",
              "city": "San Antonio Tailored",
              "county": "San Antonio Tailored County",
              "state": "Texas",
              "postcode": "",
              "country": "United States",
              "country_code": "us"
            },
            "url": "https://www.craigslist.org/view/d/san-antonio-tailored-for-pet-lovers-bed/fSLdUifh9YEQer2WzjonK6#share",
            "posting_id": "7944691682"
          }
        }
      },
      "house_ger": {
        "id": "0b2e27dd-d7b9-4db5-b8a1-ce582b04ddbf",
        "name": "Tailored for pet lovers! 2 Bed/2 Bath in our pet-friendly community.",
        "location": "2003 Oakhill Dr",
        "mainpic": "d958f140-52bf-4057-a923-624f49a60a20",
        "msg": "QR Code Link to This Post Welcome to Vivid Apartment Homes! 2003 Oakhill Dr San Antonio, TX 78238 Call us today! show contact info Rental Size: 2 BR - 2 BA - 1006 sq ft Monthly Price: $1239 *Optional and usage-based charges not included. Contact office to confirm pricing details and included fees. Lease Length: 6-Month, 12-Month Our one- and two-bedroom apartments are available in both renovated and classic styles. Renovated homes feature updated vinyl flooring, matte black fixtures, and modern finishes, while every apartment includes a fully equipped kitchen, granite-inspired countertops, and a private patio or balcony. Enjoy community amenities like our sparkling pool, fitness center, dog park, outdoor lounge, and on-site laundromat. Plus, exciting upgrades are coming soon. Our community features: ❖ Barbecue and Grilling Area ❖ Clubhouse ❖ Laundry Facility ❖ Off-street Parking ❖ Outdoor Lounge Area ❖ Pet-Friendly ❖ Bark Park ❖ Fitness Center ❖ Paid Lawn Care ❖ Sundeck ❖ Swimming Pool Our apartment features: ❖ Black Appliances ❖ Ceiling Fans in Select Units ❖ Fully-equipped Kitchen ❖ Personal Balcony or Patio ❖ Extra Storage Space ❖ Granite-inspired Countertops ❖ Tile Kitchen Backsplash ❖ Wood-inspired Flooring in Select Units Call us today! -- show contact info -- Our Pet-Policy: Pets Welcome Upon Approval. No breed, weight, or size restrictions. Limit of 2 pets per home. Non-refundable pet fee is $300. Monthly pet rent of $20 will be charged per pet. Rabies shot must be provided. Large aquariums will require additional proof of insurance. Please call office for details. Pet Amenities: Bark Park Website: www.rentalsapts.com?n=vivid&rp=fSLdUifh9YEQ&t=wb Online Application: www.rentalsapts.com?n=vivid&rp=fSLdUifh9YEQ&t=ap Schedule a Tour: www.rentalsapts.com?n=vivid&rp=fSLdUifh9YEQ&t=sch All pricing, availability, fees, and terms are subject to change without notice. EQUAL HOUSING OPPORTUNITY 7L2ZZ5J7SVJN0OH",
        "tel": "",
        "status": 1,
        "pics": "[\"27d7153dc642fe53686aea49450c2808.jpg\",\"097324a14c21aab3907f9bca0da96221.jpg\",\"bdef2a67bd079e32ec21de4900ea94dc.jpg\",\"1ef90e06e461c1e3592f60dbd3309b14.jpg\",\"73ccb4828d7d5a23ff07916b0c5bb20f.jpg\",\"daa5ab8b0265f59ee4c8be938d4b57bf.jpg\",\"4b780514a50582d660ba4c95c311f097.jpg\",\"6db2e537d0f6d4b1c8945ae6ea3bd9e8.jpg\",\"38b9fbf90609de7259760c28869e027e.jpg\",\"8c73c9dd6f4ce5dfc15c55052c3acea1.jpg\",\"947fb8e1c12fa6d80b1a237d7236724c.jpg\",\"97d330d127752fb4d4117c842e9e1a4f.jpg\",\"74aa2d68b958a333606b459a07b2a2d8.jpg\",\"256b81dabf8fe3e1ccd66575bba6b95f.jpg\",\"10972997cb2817a47672c27a90a73a66.jpg\",\"910b295992f297c2edb146bd00a4de8c.jpg\",\"325d8cfa2f4edbba40e8b1061f82abd3.jpg\",\"e4027574fbc9973f1de64f057f7d3429.jpg\",\"02ae9db90cd861378842680a898e2aad.jpg\",\"b198c9800ff286d1e5418f39bae78bbd.jpg\",\"62c55c71195f9c2d7b8e340bb2c6a63a.jpg\",\"46a8d438e06c753e3a47ed81fe4f644b.jpg\",\"3134db0e8bf98743c890ff0ec15c9c64.jpg\",\"6e96b14a331747d0d9c1382c0cb1367b.jpg\",\"81c47e97d3dd2c44ca58f75e1dc64826.jpg\",\"074533de7478fdf56c4a66d6d2f371d0.jpg\",\"2e333db7c5c1ca0c2fef8f49e24e6af3.jpg\",\"3cf50f8b693f38a937a4b77de7e2b7dc.jpg\",\"7d40e529547fb5be09ee17041a985332.jpg\",\"3e83df866bcda276f5b635f75d6e7b6c.jpg\",\"60a4a3c366d74d0d9cc808a0b4a3d511.jpg\",\"9f3f6d753752539ad33998cb02d860d1.jpg\",\"bb2c3d93167fa46b34239c55329e41dd.jpg\",\"5a3c7c0c05f74bc566ea576b6d25fe89.jpg\",\"29a324050b244838cd38051a10c103bc.jpg\",\"2949602723cf5311f2f76093b87f4acf.jpg\",\"83e5f1e45eebc7dd915bb060f1a237b1.jpg\",\"6970e3c9a2646bac53db2c851371b1a5.jpg\",\"3cb6d6ceb055f0c6e9cb9be26747bef4.jpg\",\"ff0c324846e120e45b72fab09ba434f0.jpg\",\"631e40cfcc510159f735203811ebb159.jpg\",\"4bef90193c34b988e62ce43360fdcfac.jpg\",\"caaea9b520f541dbca068ac280cef8cb.jpg\",\"7a8f65666af75d3fad1282563fb0d38a.jpg\",\"cae6c2f7173ec9be81db2ba3dce0bb0a.jpg\",\"68a443703965c17669245e23eba3d7b7.jpg\",\"533aff44266c87ea003eef16356b802b.jpg\",\"624f9faa7e7f4671b73d7dc03c014aa7.jpg\",\"84088c89c9e309d6fb35274bf00662ea.jpg\"]",
        "detail_loca1": "Texas",
        "detail_loca2": "San Antonio Tailored County",
        "detail_loca3": "San Antonio Tailored",
        "room": "2",
        "area": "1006",
        "loft": "1",
        "supplier": "Craigslist",
        "price": "$1,239",
        "ver": "House",
        "info": "QR Code Link to This Post Welcome to Vivid Apartment Homes! 2003 Oakhill Dr San Antonio, TX 78238 Call us today! show contact info Rental Size: 2 BR - 2 BA - 1006 sq ft Monthly Price: $1239 *Optional and usage-based charges not included. Contact office to confirm pricing details and included fees. Lease Length: 6-Month, 12-Month Our one- and two-bedroom apartments are available in both renovated and classic styles. Renovated homes feature updated vinyl flooring, matte black fixtures, and modern finishes, while every apartment includes a fully equipped kitchen, granite-inspired countertops, and a private patio or balcony. Enjoy community amenities like our sparkling pool, fitness center, dog park, outdoor lounge, and on-site laundromat. Plus, exciting upgrades are coming soon. Our community features: ❖ Barbecue and Grilling Area ❖ Clubhouse ❖ Laundry Facility ❖ Off-street Parking ❖ Outdoor Lounge Area ❖ Pet-Friendly ❖ Bark Park ❖ Fitness Center ❖ Paid Lawn Care ❖ Sundeck ❖ Swimming Pool Our apartment features: ❖ Black Appliances ❖ Ceiling Fans in Select Units ❖ Fully-equipped Kitchen ❖ Personal Balcony or Patio ❖ Extra Storage Space ❖ Granite-inspired Countertops ❖ Tile Kitchen Backsplash ❖ Wood-inspired Flooring in Select Units Call us today! -- show contact info -- Our Pet-Policy: Pets Welcome Upon Approval. No breed, weight, or size restrictions. Limit of 2 pets per home. Non-refundable pet fee is $300. Monthly pet rent of $20 will be charged per pet. Rabies shot must be provided. Large aquariums will require additional proof of insurance. Please call office for details. Pet Amenities: Bark Park Website: www.rentalsapts.com?n=vivid&rp=fSLdUifh9YEQ&t=wb Online Application: www.rentalsapts.com?n=vivid&rp=fSLdUifh9YEQ&t=ap Schedule a Tour: www.rentalsapts.com?n=vivid&rp=fSLdUifh9YEQ&t=sch All pricing, availability, fees, and terms are subject to change without notice. EQUAL HOUSING OPPORTUNITY 7L2ZZ5J7SVJN0OH",
        "statetype": "house",
        "street": "2003 Oakhill Dr",
        "district": "San Antonio Tailored",
        "city": "San Antonio Tailored County",
        "state": "Texas",
        "country": "United States",
        "county": "San Antonio Tailored County",
        "display_name": "2003 Oakhill Dr, San Antonio Tailored, TX",
        "address_json": "{\"source\":\"craigslist\",\"display_name\":\"2003 Oakhill Dr, San Antonio Tailored, TX\",\"address\":{\"road\":\"2003 Oakhill Dr\",\"city\":\"San Antonio Tailored\",\"county\":\"San Antonio Tailored County\",\"state\":\"Texas\",\"postcode\":\"\",\"country\":\"United States\",\"country_code\":\"us\"},\"url\":\"https://www.craigslist.org/view/d/san-antonio-tailored-for-pet-lovers-bed/fSLdUifh9YEQer2WzjonK6\",\"posting_id\":\"7944691682\"}",
        "display_state": "Texas",
        "display_city": "San Antonio Tailored County",
        "display_district": "San Antonio Tailored",
        "pic_count": 49,
        "pics_jsonStr": "[\"27d7153dc642fe53686aea49450c2808.jpg\",\"097324a14c21aab3907f9bca0da96221.jpg\",\"bdef2a67bd079e32ec21de4900ea94dc.jpg\",\"1ef90e06e461c1e3592f60dbd3309b14.jpg\",\"73ccb4828d7d5a23ff07916b0c5bb20f.jpg\",\"daa5ab8b0265f59ee4c8be938d4b57bf.jpg\",\"4b780514a50582d660ba4c95c311f097.jpg\",\"6db2e537d0f6d4b1c8945ae6ea3bd9e8.jpg\",\"38b9fbf90609de7259760c28869e027e.jpg\",\"8c73c9dd6f4ce5dfc15c55052c3acea1.jpg\",\"947fb8e1c12fa6d80b1a237d7236724c.jpg\",\"97d330d127752fb4d4117c842e9e1a4f.jpg\",\"74aa2d68b958a333606b459a07b2a2d8.jpg\",\"256b81dabf8fe3e1ccd66575bba6b95f.jpg\",\"10972997cb2817a47672c27a90a73a66.jpg\",\"910b295992f297c2edb146bd00a4de8c.jpg\",\"325d8cfa2f4edbba40e8b1061f82abd3.jpg\",\"e4027574fbc9973f1de64f057f7d3429.jpg\",\"02ae9db90cd861378842680a898e2aad.jpg\",\"b198c9800ff286d1e5418f39bae78bbd.jpg\",\"62c55c71195f9c2d7b8e340bb2c6a63a.jpg\",\"46a8d438e06c753e3a47ed81fe4f644b.jpg\",\"3134db0e8bf98743c890ff0ec15c9c64.jpg\",\"6e96b14a331747d0d9c1382c0cb1367b.jpg\",\"81c47e97d3dd2c44ca58f75e1dc64826.jpg\",\"074533de7478fdf56c4a66d6d2f371d0.jpg\",\"2e333db7c5c1ca0c2fef8f49e24e6af3.jpg\",\"3cf50f8b693f38a937a4b77de7e2b7dc.jpg\",\"7d40e529547fb5be09ee17041a985332.jpg\",\"3e83df866bcda276f5b635f75d6e7b6c.jpg\",\"60a4a3c366d74d0d9cc808a0b4a3d511.jpg\",\"9f3f6d753752539ad33998cb02d860d1.jpg\",\"bb2c3d93167fa46b34239c55329e41dd.jpg\",\"5a3c7c0c05f74bc566ea576b6d25fe89.jpg\",\"29a324050b244838cd38051a10c103bc.jpg\",\"2949602723cf5311f2f76093b87f4acf.jpg\",\"83e5f1e45eebc7dd915bb060f1a237b1.jpg\",\"6970e3c9a2646bac53db2c851371b1a5.jpg\",\"3cb6d6ceb055f0c6e9cb9be26747bef4.jpg\",\"ff0c324846e120e45b72fab09ba434f0.jpg\",\"631e40cfcc510159f735203811ebb159.jpg\",\"4bef90193c34b988e62ce43360fdcfac.jpg\",\"caaea9b520f541dbca068ac280cef8cb.jpg\",\"7a8f65666af75d3fad1282563fb0d38a.jpg\",\"cae6c2f7173ec9be81db2ba3dce0bb0a.jpg\",\"68a443703965c17669245e23eba3d7b7.jpg\",\"533aff44266c87ea003eef16356b802b.jpg\",\"624f9faa7e7f4671b73d7dc03c014aa7.jpg\",\"84088c89c9e309d6fb35274bf00662ea.jpg\"]",
        "cdkey": "cl-7944691682",
        "create_time": "7/2/2026 22:52:23",
        "update_time": "7/2/2026 22:52:23",
        "_source": {
          "craigslist_id": "7944691682",
          "url": "https://www.craigslist.org/view/d/san-antonio-tailored-for-pet-lovers-bed/fSLdUifh9YEQer2WzjonK6",
          "image_urls": [
            "https://images.craigslist.org/01414_atBKfJ1YtVu_0uY0kE_600x450.jpg",
            "https://images.craigslist.org/00T0T_5Z1OqckmSPc_0vm0l2_600x450.jpg",
            "https://images.craigslist.org/00g0g_8lWoFlbcQGS_0uY0kE_600x450.jpg",
            "https://images.craigslist.org/00Z0Z_JQvulZQ9vI_0uY0kE_600x450.jpg",
            "https://images.craigslist.org/00Y0Y_656XHJM8jfm_0uY0kE_600x450.jpg",
            "https://images.craigslist.org/00P0P_gBMgxmvSAc2_0oc0g8_600x450.jpg",
            "https://images.craigslist.org/00I0I_5AELQa2NIJv_0uY0kE_600x450.jpg",
            "https://images.craigslist.org/00Q0Q_l6FVeTkWObh_0uY0kE_600x450.jpg",
            "https://images.craigslist.org/01111_8GWweuJHTjG_0uY0kE_600x450.jpg",
            "https://images.craigslist.org/00V0V_1eY5sZiCEjf_0uY0kE_600x450.jpg",
            "https://images.craigslist.org/00J0J_kLlajyairw4_0uY0kE_600x450.jpg",
            "https://images.craigslist.org/01111_hEsoLjGuLTU_0uY0kE_600x450.jpg",
            "https://images.craigslist.org/00u0u_aUyE1BGXu59_0uY0kE_600x450.jpg",
            "https://images.craigslist.org/00Z0Z_1c8RunF19sT_0uY0kE_600x450.jpg",
            "https://images.craigslist.org/00w0w_3Xq0oTr3SyM_0uY0kE_600x450.jpg",
            "https://images.craigslist.org/00a0a_gaaZyfPXYYB_0uY0kE_600x450.jpg",
            "https://images.craigslist.org/01717_cznnYV5z57O_0uY0kE_600x450.jpg",
            "https://images.craigslist.org/00r0r_4t1njqriMZi_0uY0kE_600x450.jpg",
            "https://images.craigslist.org/00I0I_dYbYEpU3q7U_0uY0kE_600x450.jpg",
            "https://images.craigslist.org/00i0i_l8oDhL7WRms_0uY0kE_600x450.jpg",
            "https://images.craigslist.org/01515_dGzS5M8uTWk_0uY0kE_600x450.jpg",
            "https://images.craigslist.org/00j0j_3gR9lTj58Zv_0uY0kE_600x450.jpg",
            "https://images.craigslist.org/00p0p_6o1bzFw8mXC_0uY0kE_600x450.jpg",
            "https://images.craigslist.org/00W0W_1eN4oLgf0gr_0uY0uY_600x450.jpg",
            "https://images.craigslist.org/01414_atBKfJ1YtVu_0uY0kE_1200x900.jpg",
            "https://images.craigslist.org/00T0T_5Z1OqckmSPc_0vm0l2_1200x900.jpg",
            "https://images.craigslist.org/00g0g_8lWoFlbcQGS_0uY0kE_1200x900.jpg",
            "https://images.craigslist.org/00Z0Z_JQvulZQ9vI_0uY0kE_1200x900.jpg",
            "https://images.craigslist.org/00Y0Y_656XHJM8jfm_0uY0kE_1200x900.jpg",
            "https://images.craigslist.org/00P0P_gBMgxmvSAc2_0oc0g8_1200x900.jpg",
            "https://images.craigslist.org/00I0I_5AELQa2NIJv_0uY0kE_1200x900.jpg",
            "https://images.craigslist.org/00Q0Q_l6FVeTkWObh_0uY0kE_1200x900.jpg",
            "https://images.craigslist.org/01111_8GWweuJHTjG_0uY0kE_1200x900.jpg",
            "https://images.craigslist.org/00V0V_1eY5sZiCEjf_0uY0kE_1200x900.jpg",
            "https://images.craigslist.org/00J0J_kLlajyairw4_0uY0kE_1200x900.jpg",
            "https://images.craigslist.org/01111_hEsoLjGuLTU_0uY0kE_1200x900.jpg",
            "https://images.craigslist.org/00u0u_aUyE1BGXu59_0uY0kE_1200x900.jpg",
            "https://images.craigslist.org/00Z0Z_1c8RunF19sT_0uY0kE_1200x900.jpg",
            "https://images.craigslist.org/00w0w_3Xq0oTr3SyM_0uY0kE_1200x900.jpg",
            "https://images.craigslist.org/00a0a_gaaZyfPXYYB_0uY0kE_1200x900.jpg",
            "https://images.craigslist.org/01717_cznnYV5z57O_0uY0kE_1200x900.jpg",
            "https://images.craigslist.org/00r0r_4t1njqriMZi_0uY0kE_1200x900.jpg",
            "https://images.craigslist.org/00I0I_dYbYEpU3q7U_0uY0kE_1200x900.jpg",
            "https://images.craigslist.org/00i0i_l8oDhL7WRms_0uY0kE_1200x900.jpg",
            "https://images.craigslist.org/01515_dGzS5M8uTWk_0uY0kE_1200x900.jpg",
            "https://images.craigslist.org/00j0j_3gR9lTj58Zv_0uY0kE_1200x900.jpg",
            "https://images.craigslist.org/00p0p_6o1bzFw8mXC_0uY0kE_1200x900.jpg",
            "https://images.craigslist.org/00W0W_1eN4oLgf0gr_0uY0uY_1200x900.jpg",
            "https://images.craigslist.org/01414_atBKfJ1YtVu_0uY0kE_50x50c.jpg",
            "https://images.craigslist.org/00T0T_5Z1OqckmSPc_0vm0l2_50x50c.jpg",
            "https://images.craigslist.org/00g0g_8lWoFlbcQGS_0uY0kE_50x50c.jpg",
            "https://images.craigslist.org/00Z0Z_JQvulZQ9vI_0uY0kE_50x50c.jpg",
            "https://images.craigslist.org/00Y0Y_656XHJM8jfm_0uY0kE_50x50c.jpg",
            "https://images.craigslist.org/00P0P_gBMgxmvSAc2_0oc0g8_50x50c.jpg",
            "https://images.craigslist.org/00I0I_5AELQa2NIJv_0uY0kE_50x50c.jpg",
            "https://images.craigslist.org/00Q0Q_l6FVeTkWObh_0uY0kE_50x50c.jpg",
            "https://images.craigslist.org/01111_8GWweuJHTjG_0uY0kE_50x50c.jpg",
            "https://images.craigslist.org/00V0V_1eY5sZiCEjf_0uY0kE_50x50c.jpg",
            "https://images.craigslist.org/00J0J_kLlajyairw4_0uY0kE_50x50c.jpg",
            "https://images.craigslist.org/01111_hEsoLjGuLTU_0uY0kE_50x50c.jpg",
            "https://images.craigslist.org/00u0u_aUyE1BGXu59_0uY0kE_50x50c.jpg",
            "https://images.craigslist.org/00Z0Z_1c8RunF19sT_0uY0kE_50x50c.jpg",
            "https://images.craigslist.org/00w0w_3Xq0oTr3SyM_0uY0kE_50x50c.jpg",
            "https://images.craigslist.org/00a0a_gaaZyfPXYYB_0uY0kE_50x50c.jpg",
            "https://images.craigslist.org/01717_cznnYV5z57O_0uY0kE_50x50c.jpg",
            "https://images.craigslist.org/00r0r_4t1njqriMZi_0uY0kE_50x50c.jpg",
            "https://images.craigslist.org/00I0I_dYbYEpU3q7U_0uY0kE_50x50c.jpg",
            "https://images.craigslist.org/00i0i_l8oDhL7WRms_0uY0kE_50x50c.jpg",
            "https://images.craigslist.org/01515_dGzS5M8uTWk_0uY0kE_50x50c.jpg",
            "https://images.craigslist.org/00j0j_3gR9lTj58Zv_0uY0kE_50x50c.jpg",
            "https://images.craigslist.org/00p0p_6o1bzFw8mXC_0uY0kE_50x50c.jpg",
            "https://images.craigslist.org/00W0W_1eN4oLgf0gr_0uY0uY_50x50c.jpg"
          ],
          "image_dir": "d958f140-52bf-4057-a923-624f49a60a20"
        }
      }
    },
    {
      "craigslist": {
        "url": "https://www.craigslist.org/view/d/san-antonio-tailored-for-pet-lovers-bed/fSLdUifh9YEQer2WzjonK6#share",
        "posting_id": "7944691682",
        "title": "Tailored for pet lovers! 2 Bed/2 Bath in our pet-friendly community.",
        "price": 1239,
        "price_text": "$1,239",
        "room": 2,
        "area": "1006",
        "loft": "1",
        "location": "2003 Oakhill Dr",
        "full_address": "2003 Oakhill Dr, San Antonio Tailored",
        "locality": "San Antonio Tailored",
        "geocode_query": "2003 Oakhill Dr, San Antonio Tailored",
        "description": "QR Code Link to This Post Welcome to Vivid Apartment Homes! 2003 Oakhill Dr San Antonio, TX 78238 Call us today! show contact info Rental Size: 2 BR - 2 BA - 1006 sq ft Monthly Price: $1239 *Optional and usage-based charges not included. Contact office to confirm pricing details and included fees. Lease Length: 6-Month, 12-Month Our one- and two-bedroom apartments are available in both renovated and classic styles. Renovated homes feature updated vinyl flooring, matte black fixtures, and modern finishes, while every apartment includes a fully equipped kitchen, granite-inspired countertops, and a private patio or balcony. Enjoy community amenities like our sparkling pool, fitness center, dog park, outdoor lounge, and on-site laundromat. Plus, exciting upgrades are coming soon. Our community features: ❖ Barbecue and Grilling Area ❖ Clubhouse ❖ Laundry Facility ❖ Off-street Parking ❖ Outdoor Lounge Area ❖ Pet-Friendly ❖ Bark Park ❖ Fitness Center ❖ Paid Lawn Care ❖ Sundeck ❖ Swimming Pool Our apartment features: ❖ Black Appliances ❖ Ceiling Fans in Select Units ❖ Fully-equipped Kitchen ❖ Personal Balcony or Patio ❖ Extra Storage Space ❖ Granite-inspired Countertops ❖ Tile Kitchen Backsplash ❖ Wood-inspired Flooring in Select Units Call us today! -- show contact info -- Our Pet-Policy: Pets Welcome Upon Approval. No breed, weight, or size restrictions. Limit of 2 pets per home. Non-refundable pet fee is $300. Monthly pet rent of $20 will be charged per pet. Rabies shot must be provided. Large aquariums will require additional proof of insurance. Please call office for details. Pet Amenities: Bark Park Website: www.rentalsapts.com?n=vivid&rp=fSLdUifh9YEQ&t=wb Online Application: www.rentalsapts.com?n=vivid&rp=fSLdUifh9YEQ&t=ap Schedule a Tour: www.rentalsapts.com?n=vivid&rp=fSLdUifh9YEQ&t=sch All pricing, availability, fees, and terms are subject to change without notice. EQUAL HOUSING OPPORTUNITY 7L2ZZ5J7SVJN0OH",
        "phone": "",
        "image_urls": [
          "https://images.craigslist.org/01414_atBKfJ1YtVu_0uY0kE_600x450.jpg",
          "https://images.craigslist.org/00T0T_5Z1OqckmSPc_0vm0l2_600x450.jpg",
          "https://images.craigslist.org/00g0g_8lWoFlbcQGS_0uY0kE_600x450.jpg",
          "https://images.craigslist.org/00Z0Z_JQvulZQ9vI_0uY0kE_600x450.jpg",
          "https://images.craigslist.org/00Y0Y_656XHJM8jfm_0uY0kE_600x450.jpg",
          "https://images.craigslist.org/00P0P_gBMgxmvSAc2_0oc0g8_600x450.jpg",
          "https://images.craigslist.org/00I0I_5AELQa2NIJv_0uY0kE_600x450.jpg",
          "https://images.craigslist.org/00Q0Q_l6FVeTkWObh_0uY0kE_600x450.jpg",
          "https://images.craigslist.org/01111_8GWweuJHTjG_0uY0kE_600x450.jpg",
          "https://images.craigslist.org/00V0V_1eY5sZiCEjf_0uY0kE_600x450.jpg",
          "https://images.craigslist.org/00J0J_kLlajyairw4_0uY0kE_600x450.jpg",
          "https://images.craigslist.org/01111_hEsoLjGuLTU_0uY0kE_600x450.jpg",
          "https://images.craigslist.org/00u0u_aUyE1BGXu59_0uY0kE_600x450.jpg",
          "https://images.craigslist.org/00Z0Z_1c8RunF19sT_0uY0kE_600x450.jpg",
          "https://images.craigslist.org/00w0w_3Xq0oTr3SyM_0uY0kE_600x450.jpg",
          "https://images.craigslist.org/00a0a_gaaZyfPXYYB_0uY0kE_600x450.jpg",
          "https://images.craigslist.org/01717_cznnYV5z57O_0uY0kE_600x450.jpg",
          "https://images.craigslist.org/00r0r_4t1njqriMZi_0uY0kE_600x450.jpg",
          "https://images.craigslist.org/00I0I_dYbYEpU3q7U_0uY0kE_600x450.jpg",
          "https://images.craigslist.org/00i0i_l8oDhL7WRms_0uY0kE_600x450.jpg",
          "https://images.craigslist.org/01515_dGzS5M8uTWk_0uY0kE_600x450.jpg",
          "https://images.craigslist.org/00j0j_3gR9lTj58Zv_0uY0kE_600x450.jpg",
          "https://images.craigslist.org/00p0p_6o1bzFw8mXC_0uY0kE_600x450.jpg",
          "https://images.craigslist.org/00W0W_1eN4oLgf0gr_0uY0uY_600x450.jpg",
          "https://images.craigslist.org/01414_atBKfJ1YtVu_0uY0kE_1200x900.jpg",
          "https://images.craigslist.org/00T0T_5Z1OqckmSPc_0vm0l2_1200x900.jpg",
          "https://images.craigslist.org/00g0g_8lWoFlbcQGS_0uY0kE_1200x900.jpg",
          "https://images.craigslist.org/00Z0Z_JQvulZQ9vI_0uY0kE_1200x900.jpg",
          "https://images.craigslist.org/00Y0Y_656XHJM8jfm_0uY0kE_1200x900.jpg",
          "https://images.craigslist.org/00P0P_gBMgxmvSAc2_0oc0g8_1200x900.jpg",
          "https://images.craigslist.org/00I0I_5AELQa2NIJv_0uY0kE_1200x900.jpg",
          "https://images.craigslist.org/00Q0Q_l6FVeTkWObh_0uY0kE_1200x900.jpg",
          "https://images.craigslist.org/01111_8GWweuJHTjG_0uY0kE_1200x900.jpg",
          "https://images.craigslist.org/00V0V_1eY5sZiCEjf_0uY0kE_1200x900.jpg",
          "https://images.craigslist.org/00J0J_kLlajyairw4_0uY0kE_1200x900.jpg",
          "https://images.craigslist.org/01111_hEsoLjGuLTU_0uY0kE_1200x900.jpg",
          "https://images.craigslist.org/00u0u_aUyE1BGXu59_0uY0kE_1200x900.jpg",
          "https://images.craigslist.org/00Z0Z_1c8RunF19sT_0uY0kE_1200x900.jpg",
          "https://images.craigslist.org/00w0w_3Xq0oTr3SyM_0uY0kE_1200x900.jpg",
          "https://images.craigslist.org/00a0a_gaaZyfPXYYB_0uY0kE_1200x900.jpg",
          "https://images.craigslist.org/01717_cznnYV5z57O_0uY0kE_1200x900.jpg",
          "https://images.craigslist.org/00r0r_4t1njqriMZi_0uY0kE_1200x900.jpg",
          "https://images.craigslist.org/00I0I_dYbYEpU3q7U_0uY0kE_1200x900.jpg",
          "https://images.craigslist.org/00i0i_l8oDhL7WRms_0uY0kE_1200x900.jpg",
          "https://images.craigslist.org/01515_dGzS5M8uTWk_0uY0kE_1200x900.jpg",
          "https://images.craigslist.org/00j0j_3gR9lTj58Zv_0uY0kE_1200x900.jpg",
          "https://images.craigslist.org/00p0p_6o1bzFw8mXC_0uY0kE_1200x900.jpg",
          "https://images.craigslist.org/00W0W_1eN4oLgf0gr_0uY0uY_1200x900.jpg",
          "https://images.craigslist.org/01414_atBKfJ1YtVu_0uY0kE_50x50c.jpg",
          "https://images.craigslist.org/00T0T_5Z1OqckmSPc_0vm0l2_50x50c.jpg",
          "https://images.craigslist.org/00g0g_8lWoFlbcQGS_0uY0kE_50x50c.jpg",
          "https://images.craigslist.org/00Z0Z_JQvulZQ9vI_0uY0kE_50x50c.jpg",
          "https://images.craigslist.org/00Y0Y_656XHJM8jfm_0uY0kE_50x50c.jpg",
          "https://images.craigslist.org/00P0P_gBMgxmvSAc2_0oc0g8_50x50c.jpg",
          "https://images.craigslist.org/00I0I_5AELQa2NIJv_0uY0kE_50x50c.jpg",
          "https://images.craigslist.org/00Q0Q_l6FVeTkWObh_0uY0kE_50x50c.jpg",
          "https://images.craigslist.org/01111_8GWweuJHTjG_0uY0kE_50x50c.jpg",
          "https://images.craigslist.org/00V0V_1eY5sZiCEjf_0uY0kE_50x50c.jpg",
          "https://images.craigslist.org/00J0J_kLlajyairw4_0uY0kE_50x50c.jpg",
          "https://images.craigslist.org/01111_hEsoLjGuLTU_0uY0kE_50x50c.jpg",
          "https://images.craigslist.org/00u0u_aUyE1BGXu59_0uY0kE_50x50c.jpg",
          "https://images.craigslist.org/00Z0Z_1c8RunF19sT_0uY0kE_50x50c.jpg",
          "https://images.craigslist.org/00w0w_3Xq0oTr3SyM_0uY0kE_50x50c.jpg",
          "https://images.craigslist.org/00a0a_gaaZyfPXYYB_0uY0kE_50x50c.jpg",
          "https://images.craigslist.org/01717_cznnYV5z57O_0uY0kE_50x50c.jpg",
          "https://images.craigslist.org/00r0r_4t1njqriMZi_0uY0kE_50x50c.jpg",
          "https://images.craigslist.org/00I0I_dYbYEpU3q7U_0uY0kE_50x50c.jpg",
          "https://images.craigslist.org/00i0i_l8oDhL7WRms_0uY0kE_50x50c.jpg",
          "https://images.craigslist.org/01515_dGzS5M8uTWk_0uY0kE_50x50c.jpg",
          "https://images.craigslist.org/00j0j_3gR9lTj58Zv_0uY0kE_50x50c.jpg",
          "https://images.craigslist.org/00p0p_6o1bzFw8mXC_0uY0kE_50x50c.jpg",
          "https://images.craigslist.org/00W0W_1eN4oLgf0gr_0uY0uY_50x50c.jpg"
        ],
        "housing_type": "house",
        "baths": 2,
        "image_files": [
          "21eeca06758de1941bc721c51887d3cc.jpg",
          "379292099c7858e85ccc67723a5f35df.jpg",
          "8cb42d9a7ef25efd8aff22025b18e701.jpg",
          "c8d887226cba66ce6b1e3e00b8182ca8.jpg",
          "961a57f8fab2f499f3dcbbb951f2a802.jpg",
          "050c824cb76851dafe3ab97fb89d32cf.jpg",
          "4d89ee5c224082fc83c0346398b3f83e.jpg",
          "03ba3e7e633ea82405fbb1700e59c10d.jpg",
          "f382dfed1a56879ee75124a0879c1092.jpg",
          "2564acc923cf42fe31ec13030d4c7ecd.jpg",
          "3b01bb45ca0c62da715afb3016d00c61.jpg",
          "18433085c4ba2b347ea630858320c16c.jpg",
          "8c2bb0dfd8b451a8f04cbb35e10acbb8.jpg",
          "61216fb7a8bd6283818f6bfc1d3b285b.jpg",
          "96bbc71eb3b87b805a5c646b38b4c8c3.jpg",
          "81c4e7b5b631e261d1299a888923df32.jpg",
          "ca78ba06d7dce8b6b9505e1eedda345e.jpg",
          "1c74b4628864ea770463fc8e34a26990.jpg",
          "05ea52177e9c3aaa91b6a656f1e3d0f4.jpg",
          "324f44434d724c4a3ee49c5917a0a0bd.jpg",
          "a236399d64deb27c23e7ddfd4743c169.jpg",
          "662bc659558872e79f2b0e9c3635d1aa.jpg",
          "631b50423c1341d96ec6c8c8d366d8c7.jpg",
          "22f2d3e91ac4467348612ba6107169c0.jpg",
          "50f7e3293646797a8b1b95f225697eb6.jpg",
          "ee1d20267e6389bf227b7f524893ca71.jpg",
          "3ed225752ec8323c2cba0a31b55f8f89.jpg",
          "d3a39721d328fb70e53ee68acc2fddec.jpg",
          "67ac4d82c493497c1c9c798a4693f730.jpg",
          "e39e7c0e0e4f96f84f338689209e63ad.jpg",
          "ba472d4f18bebc10c184067df63456e5.jpg",
          "4761ce39cf8a9a0522ba8ac0848a39ac.jpg",
          "6372674e12ee46818ac5fe29d6e42d7c.jpg",
          "edead609d84d1a66a2bc7cf29927cbb4.jpg",
          "64717b09bcc936f801907b6e8e2bf2d6.jpg",
          "6aa39321540d834b5fac7cee0c451014.jpg",
          "f8e696e54e62523db048f3eb2cfb412f.jpg",
          "2740ca80ccddfaf47937fdbb1a43a64d.jpg",
          "7b825e6ae5004beb5407fce667146e96.jpg",
          "6aaa94d370d58a9474064cf3977a4089.jpg",
          "f02bc1dc58744af07eae14bb54b0f868.jpg",
          "8d659f5d2bdf61f7ac60ffa5af22e136.jpg",
          "63a1363d3c69647cb14dcc29ab5e8471.jpg",
          "9b62bdb4eaed1e9d2cc9d887e6c14b20.jpg",
          "d2dfca4c60f145c8c12681c991032f20.jpg",
          "d67f4ac73ac6f00c155683d532a5d4bd.jpg",
          "19c2ebaec3973493d67649eaf476c056.jpg",
          "2641089ab025797f1fea23a3e4ea8df9.jpg",
          "fd23aea846d62baca7acde8af9bd1668.jpg"
        ],
        "mainpic": "472f1e66-7e38-4915-b12a-521f5e10cb5c",
        "geo": {
          "street": "2003 Oakhill Dr",
          "display_state": "Texas",
          "display_city": "San Antonio Tailored County",
          "display_district": "San Antonio Tailored",
          "display_name": "2003 Oakhill Dr, San Antonio Tailored, TX",
          "lat": null,
          "lon": null,
          "address_json": {
            "source": "craigslist",
            "display_name": "2003 Oakhill Dr, San Antonio Tailored, TX",
            "address": {
              "road": "2003 Oakhill Dr",
              "city": "San Antonio Tailored",
              "county": "San Antonio Tailored County",
              "state": "Texas",
              "postcode": "",
              "country": "United States",
              "country_code": "us"
            },
            "url": "https://www.craigslist.org/view/d/san-antonio-tailored-for-pet-lovers-bed/fSLdUifh9YEQer2WzjonK6#share",
            "posting_id": "7944691682"
          }
        }
      },
      "house_ger": {
        "id": "4ef5578e-9cf2-4b63-b5e1-46d16c1eb0f6",
        "name": "Tailored for pet lovers! 2 Bed/2 Bath in our pet-friendly community.",
        "location": "2003 Oakhill Dr",
        "mainpic": "472f1e66-7e38-4915-b12a-521f5e10cb5c",
        "msg": "QR Code Link to This Post Welcome to Vivid Apartment Homes! 2003 Oakhill Dr San Antonio, TX 78238 Call us today! show contact info Rental Size: 2 BR - 2 BA - 1006 sq ft Monthly Price: $1239 *Optional and usage-based charges not included. Contact office to confirm pricing details and included fees. Lease Length: 6-Month, 12-Month Our one- and two-bedroom apartments are available in both renovated and classic styles. Renovated homes feature updated vinyl flooring, matte black fixtures, and modern finishes, while every apartment includes a fully equipped kitchen, granite-inspired countertops, and a private patio or balcony. Enjoy community amenities like our sparkling pool, fitness center, dog park, outdoor lounge, and on-site laundromat. Plus, exciting upgrades are coming soon. Our community features: ❖ Barbecue and Grilling Area ❖ Clubhouse ❖ Laundry Facility ❖ Off-street Parking ❖ Outdoor Lounge Area ❖ Pet-Friendly ❖ Bark Park ❖ Fitness Center ❖ Paid Lawn Care ❖ Sundeck ❖ Swimming Pool Our apartment features: ❖ Black Appliances ❖ Ceiling Fans in Select Units ❖ Fully-equipped Kitchen ❖ Personal Balcony or Patio ❖ Extra Storage Space ❖ Granite-inspired Countertops ❖ Tile Kitchen Backsplash ❖ Wood-inspired Flooring in Select Units Call us today! -- show contact info -- Our Pet-Policy: Pets Welcome Upon Approval. No breed, weight, or size restrictions. Limit of 2 pets per home. Non-refundable pet fee is $300. Monthly pet rent of $20 will be charged per pet. Rabies shot must be provided. Large aquariums will require additional proof of insurance. Please call office for details. Pet Amenities: Bark Park Website: www.rentalsapts.com?n=vivid&rp=fSLdUifh9YEQ&t=wb Online Application: www.rentalsapts.com?n=vivid&rp=fSLdUifh9YEQ&t=ap Schedule a Tour: www.rentalsapts.com?n=vivid&rp=fSLdUifh9YEQ&t=sch All pricing, availability, fees, and terms are subject to change without notice. EQUAL HOUSING OPPORTUNITY 7L2ZZ5J7SVJN0OH",
        "tel": "",
        "status": 1,
        "pics": "[\"21eeca06758de1941bc721c51887d3cc.jpg\",\"379292099c7858e85ccc67723a5f35df.jpg\",\"8cb42d9a7ef25efd8aff22025b18e701.jpg\",\"c8d887226cba66ce6b1e3e00b8182ca8.jpg\",\"961a57f8fab2f499f3dcbbb951f2a802.jpg\",\"050c824cb76851dafe3ab97fb89d32cf.jpg\",\"4d89ee5c224082fc83c0346398b3f83e.jpg\",\"03ba3e7e633ea82405fbb1700e59c10d.jpg\",\"f382dfed1a56879ee75124a0879c1092.jpg\",\"2564acc923cf42fe31ec13030d4c7ecd.jpg\",\"3b01bb45ca0c62da715afb3016d00c61.jpg\",\"18433085c4ba2b347ea630858320c16c.jpg\",\"8c2bb0dfd8b451a8f04cbb35e10acbb8.jpg\",\"61216fb7a8bd6283818f6bfc1d3b285b.jpg\",\"96bbc71eb3b87b805a5c646b38b4c8c3.jpg\",\"81c4e7b5b631e261d1299a888923df32.jpg\",\"ca78ba06d7dce8b6b9505e1eedda345e.jpg\",\"1c74b4628864ea770463fc8e34a26990.jpg\",\"05ea52177e9c3aaa91b6a656f1e3d0f4.jpg\",\"324f44434d724c4a3ee49c5917a0a0bd.jpg\",\"a236399d64deb27c23e7ddfd4743c169.jpg\",\"662bc659558872e79f2b0e9c3635d1aa.jpg\",\"631b50423c1341d96ec6c8c8d366d8c7.jpg\",\"22f2d3e91ac4467348612ba6107169c0.jpg\",\"50f7e3293646797a8b1b95f225697eb6.jpg\",\"ee1d20267e6389bf227b7f524893ca71.jpg\",\"3ed225752ec8323c2cba0a31b55f8f89.jpg\",\"d3a39721d328fb70e53ee68acc2fddec.jpg\",\"67ac4d82c493497c1c9c798a4693f730.jpg\",\"e39e7c0e0e4f96f84f338689209e63ad.jpg\",\"ba472d4f18bebc10c184067df63456e5.jpg\",\"4761ce39cf8a9a0522ba8ac0848a39ac.jpg\",\"6372674e12ee46818ac5fe29d6e42d7c.jpg\",\"edead609d84d1a66a2bc7cf29927cbb4.jpg\",\"64717b09bcc936f801907b6e8e2bf2d6.jpg\",\"6aa39321540d834b5fac7cee0c451014.jpg\",\"f8e696e54e62523db048f3eb2cfb412f.jpg\",\"2740ca80ccddfaf47937fdbb1a43a64d.jpg\",\"7b825e6ae5004beb5407fce667146e96.jpg\",\"6aaa94d370d58a9474064cf3977a4089.jpg\",\"f02bc1dc58744af07eae14bb54b0f868.jpg\",\"8d659f5d2bdf61f7ac60ffa5af22e136.jpg\",\"63a1363d3c69647cb14dcc29ab5e8471.jpg\",\"9b62bdb4eaed1e9d2cc9d887e6c14b20.jpg\",\"d2dfca4c60f145c8c12681c991032f20.jpg\",\"d67f4ac73ac6f00c155683d532a5d4bd.jpg\",\"19c2ebaec3973493d67649eaf476c056.jpg\",\"2641089ab025797f1fea23a3e4ea8df9.jpg\",\"fd23aea846d62baca7acde8af9bd1668.jpg\"]",
        "detail_loca1": "Texas",
        "detail_loca2": "San Antonio Tailored County",
        "detail_loca3": "San Antonio Tailored",
        "room": "2",
        "area": "1006",
        "loft": "1",
        "supplier": "Craigslist",
        "price": "$1,239",
        "ver": "House",
        "info": "QR Code Link to This Post Welcome to Vivid Apartment Homes! 2003 Oakhill Dr San Antonio, TX 78238 Call us today! show contact info Rental Size: 2 BR - 2 BA - 1006 sq ft Monthly Price: $1239 *Optional and usage-based charges not included. Contact office to confirm pricing details and included fees. Lease Length: 6-Month, 12-Month Our one- and two-bedroom apartments are available in both renovated and classic styles. Renovated homes feature updated vinyl flooring, matte black fixtures, and modern finishes, while every apartment includes a fully equipped kitchen, granite-inspired countertops, and a private patio or balcony. Enjoy community amenities like our sparkling pool, fitness center, dog park, outdoor lounge, and on-site laundromat. Plus, exciting upgrades are coming soon. Our community features: ❖ Barbecue and Grilling Area ❖ Clubhouse ❖ Laundry Facility ❖ Off-street Parking ❖ Outdoor Lounge Area ❖ Pet-Friendly ❖ Bark Park ❖ Fitness Center ❖ Paid Lawn Care ❖ Sundeck ❖ Swimming Pool Our apartment features: ❖ Black Appliances ❖ Ceiling Fans in Select Units ❖ Fully-equipped Kitchen ❖ Personal Balcony or Patio ❖ Extra Storage Space ❖ Granite-inspired Countertops ❖ Tile Kitchen Backsplash ❖ Wood-inspired Flooring in Select Units Call us today! -- show contact info -- Our Pet-Policy: Pets Welcome Upon Approval. No breed, weight, or size restrictions. Limit of 2 pets per home. Non-refundable pet fee is $300. Monthly pet rent of $20 will be charged per pet. Rabies shot must be provided. Large aquariums will require additional proof of insurance. Please call office for details. Pet Amenities: Bark Park Website: www.rentalsapts.com?n=vivid&rp=fSLdUifh9YEQ&t=wb Online Application: www.rentalsapts.com?n=vivid&rp=fSLdUifh9YEQ&t=ap Schedule a Tour: www.rentalsapts.com?n=vivid&rp=fSLdUifh9YEQ&t=sch All pricing, availability, fees, and terms are subject to change without notice. EQUAL HOUSING OPPORTUNITY 7L2ZZ5J7SVJN0OH",
        "statetype": "house",
        "street": "2003 Oakhill Dr",
        "district": "San Antonio Tailored",
        "city": "San Antonio Tailored County",
        "state": "Texas",
        "country": "United States",
        "county": "San Antonio Tailored County",
        "display_name": "2003 Oakhill Dr, San Antonio Tailored, TX",
        "address_json": "{\"source\":\"craigslist\",\"display_name\":\"2003 Oakhill Dr, San Antonio Tailored, TX\",\"address\":{\"road\":\"2003 Oakhill Dr\",\"city\":\"San Antonio Tailored\",\"county\":\"San Antonio Tailored County\",\"state\":\"Texas\",\"postcode\":\"\",\"country\":\"United States\",\"country_code\":\"us\"},\"url\":\"https://www.craigslist.org/view/d/san-antonio-tailored-for-pet-lovers-bed/fSLdUifh9YEQer2WzjonK6#share\",\"posting_id\":\"7944691682\"}",
        "display_state": "Texas",
        "display_city": "San Antonio Tailored County",
        "display_district": "San Antonio Tailored",
        "pic_count": 49,
        "pics_jsonStr": "[\"21eeca06758de1941bc721c51887d3cc.jpg\",\"379292099c7858e85ccc67723a5f35df.jpg\",\"8cb42d9a7ef25efd8aff22025b18e701.jpg\",\"c8d887226cba66ce6b1e3e00b8182ca8.jpg\",\"961a57f8fab2f499f3dcbbb951f2a802.jpg\",\"050c824cb76851dafe3ab97fb89d32cf.jpg\",\"4d89ee5c224082fc83c0346398b3f83e.jpg\",\"03ba3e7e633ea82405fbb1700e59c10d.jpg\",\"f382dfed1a56879ee75124a0879c1092.jpg\",\"2564acc923cf42fe31ec13030d4c7ecd.jpg\",\"3b01bb45ca0c62da715afb3016d00c61.jpg\",\"18433085c4ba2b347ea630858320c16c.jpg\",\"8c2bb0dfd8b451a8f04cbb35e10acbb8.jpg\",\"61216fb7a8bd6283818f6bfc1d3b285b.jpg\",\"96bbc71eb3b87b805a5c646b38b4c8c3.jpg\",\"81c4e7b5b631e261d1299a888923df32.jpg\",\"ca78ba06d7dce8b6b9505e1eedda345e.jpg\",\"1c74b4628864ea770463fc8e34a26990.jpg\",\"05ea52177e9c3aaa91b6a656f1e3d0f4.jpg\",\"324f44434d724c4a3ee49c5917a0a0bd.jpg\",\"a236399d64deb27c23e7ddfd4743c169.jpg\",\"662bc659558872e79f2b0e9c3635d1aa.jpg\",\"631b50423c1341d96ec6c8c8d366d8c7.jpg\",\"22f2d3e91ac4467348612ba6107169c0.jpg\",\"50f7e3293646797a8b1b95f225697eb6.jpg\",\"ee1d20267e6389bf227b7f524893ca71.jpg\",\"3ed225752ec8323c2cba0a31b55f8f89.jpg\",\"d3a39721d328fb70e53ee68acc2fddec.jpg\",\"67ac4d82c493497c1c9c798a4693f730.jpg\",\"e39e7c0e0e4f96f84f338689209e63ad.jpg\",\"ba472d4f18bebc10c184067df63456e5.jpg\",\"4761ce39cf8a9a0522ba8ac0848a39ac.jpg\",\"6372674e12ee46818ac5fe29d6e42d7c.jpg\",\"edead609d84d1a66a2bc7cf29927cbb4.jpg\",\"64717b09bcc936f801907b6e8e2bf2d6.jpg\",\"6aa39321540d834b5fac7cee0c451014.jpg\",\"f8e696e54e62523db048f3eb2cfb412f.jpg\",\"2740ca80ccddfaf47937fdbb1a43a64d.jpg\",\"7b825e6ae5004beb5407fce667146e96.jpg\",\"6aaa94d370d58a9474064cf3977a4089.jpg\",\"f02bc1dc58744af07eae14bb54b0f868.jpg\",\"8d659f5d2bdf61f7ac60ffa5af22e136.jpg\",\"63a1363d3c69647cb14dcc29ab5e8471.jpg\",\"9b62bdb4eaed1e9d2cc9d887e6c14b20.jpg\",\"d2dfca4c60f145c8c12681c991032f20.jpg\",\"d67f4ac73ac6f00c155683d532a5d4bd.jpg\",\"19c2ebaec3973493d67649eaf476c056.jpg\",\"2641089ab025797f1fea23a3e4ea8df9.jpg\",\"fd23aea846d62baca7acde8af9bd1668.jpg\"]",
        "cdkey": "cl-7944691682",
        "create_time": "7/2/2026 22:52:31",
        "update_time": "7/2/2026 22:52:31",
        "_source": {
          "craigslist_id": "7944691682",
          "url": "https://www.craigslist.org/view/d/san-antonio-tailored-for-pet-lovers-bed/fSLdUifh9YEQer2WzjonK6#share",
          "image_urls": [
            "https://images.craigslist.org/01414_atBKfJ1YtVu_0uY0kE_600x450.jpg",
            "https://images.craigslist.org/00T0T_5Z1OqckmSPc_0vm0l2_600x450.jpg",
            "https://images.craigslist.org/00g0g_8lWoFlbcQGS_0uY0kE_600x450.jpg",
            "https://images.craigslist.org/00Z0Z_JQvulZQ9vI_0uY0kE_600x450.jpg",
            "https://images.craigslist.org/00Y0Y_656XHJM8jfm_0uY0kE_600x450.jpg",
            "https://images.craigslist.org/00P0P_gBMgxmvSAc2_0oc0g8_600x450.jpg",
            "https://images.craigslist.org/00I0I_5AELQa2NIJv_0uY0kE_600x450.jpg",
            "https://images.craigslist.org/00Q0Q_l6FVeTkWObh_0uY0kE_600x450.jpg",
            "https://images.craigslist.org/01111_8GWweuJHTjG_0uY0kE_600x450.jpg",
            "https://images.craigslist.org/00V0V_1eY5sZiCEjf_0uY0kE_600x450.jpg",
            "https://images.craigslist.org/00J0J_kLlajyairw4_0uY0kE_600x450.jpg",
            "https://images.craigslist.org/01111_hEsoLjGuLTU_0uY0kE_600x450.jpg",
            "https://images.craigslist.org/00u0u_aUyE1BGXu59_0uY0kE_600x450.jpg",
            "https://images.craigslist.org/00Z0Z_1c8RunF19sT_0uY0kE_600x450.jpg",
            "https://images.craigslist.org/00w0w_3Xq0oTr3SyM_0uY0kE_600x450.jpg",
            "https://images.craigslist.org/00a0a_gaaZyfPXYYB_0uY0kE_600x450.jpg",
            "https://images.craigslist.org/01717_cznnYV5z57O_0uY0kE_600x450.jpg",
            "https://images.craigslist.org/00r0r_4t1njqriMZi_0uY0kE_600x450.jpg",
            "https://images.craigslist.org/00I0I_dYbYEpU3q7U_0uY0kE_600x450.jpg",
            "https://images.craigslist.org/00i0i_l8oDhL7WRms_0uY0kE_600x450.jpg",
            "https://images.craigslist.org/01515_dGzS5M8uTWk_0uY0kE_600x450.jpg",
            "https://images.craigslist.org/00j0j_3gR9lTj58Zv_0uY0kE_600x450.jpg",
            "https://images.craigslist.org/00p0p_6o1bzFw8mXC_0uY0kE_600x450.jpg",
            "https://images.craigslist.org/00W0W_1eN4oLgf0gr_0uY0uY_600x450.jpg",
            "https://images.craigslist.org/01414_atBKfJ1YtVu_0uY0kE_1200x900.jpg",
            "https://images.craigslist.org/00T0T_5Z1OqckmSPc_0vm0l2_1200x900.jpg",
            "https://images.craigslist.org/00g0g_8lWoFlbcQGS_0uY0kE_1200x900.jpg",
            "https://images.craigslist.org/00Z0Z_JQvulZQ9vI_0uY0kE_1200x900.jpg",
            "https://images.craigslist.org/00Y0Y_656XHJM8jfm_0uY0kE_1200x900.jpg",
            "https://images.craigslist.org/00P0P_gBMgxmvSAc2_0oc0g8_1200x900.jpg",
            "https://images.craigslist.org/00I0I_5AELQa2NIJv_0uY0kE_1200x900.jpg",
            "https://images.craigslist.org/00Q0Q_l6FVeTkWObh_0uY0kE_1200x900.jpg",
            "https://images.craigslist.org/01111_8GWweuJHTjG_0uY0kE_1200x900.jpg",
            "https://images.craigslist.org/00V0V_1eY5sZiCEjf_0uY0kE_1200x900.jpg",
            "https://images.craigslist.org/00J0J_kLlajyairw4_0uY0kE_1200x900.jpg",
            "https://images.craigslist.org/01111_hEsoLjGuLTU_0uY0kE_1200x900.jpg",
            "https://images.craigslist.org/00u0u_aUyE1BGXu59_0uY0kE_1200x900.jpg",
            "https://images.craigslist.org/00Z0Z_1c8RunF19sT_0uY0kE_1200x900.jpg",
            "https://images.craigslist.org/00w0w_3Xq0oTr3SyM_0uY0kE_1200x900.jpg",
            "https://images.craigslist.org/00a0a_gaaZyfPXYYB_0uY0kE_1200x900.jpg",
            "https://images.craigslist.org/01717_cznnYV5z57O_0uY0kE_1200x900.jpg",
            "https://images.craigslist.org/00r0r_4t1njqriMZi_0uY0kE_1200x900.jpg",
            "https://images.craigslist.org/00I0I_dYbYEpU3q7U_0uY0kE_1200x900.jpg",
            "https://images.craigslist.org/00i0i_l8oDhL7WRms_0uY0kE_1200x900.jpg",
            "https://images.craigslist.org/01515_dGzS5M8uTWk_0uY0kE_1200x900.jpg",
            "https://images.craigslist.org/00j0j_3gR9lTj58Zv_0uY0kE_1200x900.jpg",
            "https://images.craigslist.org/00p0p_6o1bzFw8mXC_0uY0kE_1200x900.jpg",
            "https://images.craigslist.org/00W0W_1eN4oLgf0gr_0uY0uY_1200x900.jpg",
            "https://images.craigslist.org/01414_atBKfJ1YtVu_0uY0kE_50x50c.jpg",
            "https://images.craigslist.org/00T0T_5Z1OqckmSPc_0vm0l2_50x50c.jpg",
            "https://images.craigslist.org/00g0g_8lWoFlbcQGS_0uY0kE_50x50c.jpg",
            "https://images.craigslist.org/00Z0Z_JQvulZQ9vI_0uY0kE_50x50c.jpg",
            "https://images.craigslist.org/00Y0Y_656XHJM8jfm_0uY0kE_50x50c.jpg",
            "https://images.craigslist.org/00P0P_gBMgxmvSAc2_0oc0g8_50x50c.jpg",
            "https://images.craigslist.org/00I0I_5AELQa2NIJv_0uY0kE_50x50c.jpg",
            "https://images.craigslist.org/00Q0Q_l6FVeTkWObh_0uY0kE_50x50c.jpg",
            "https://images.craigslist.org/01111_8GWweuJHTjG_0uY0kE_50x50c.jpg",
            "https://images.craigslist.org/00V0V_1eY5sZiCEjf_0uY0kE_50x50c.jpg",
            "https://images.craigslist.org/00J0J_kLlajyairw4_0uY0kE_50x50c.jpg",
            "https://images.craigslist.org/01111_hEsoLjGuLTU_0uY0kE_50x50c.jpg",
            "https://images.craigslist.org/00u0u_aUyE1BGXu59_0uY0kE_50x50c.jpg",
            "https://images.craigslist.org/00Z0Z_1c8RunF19sT_0uY0kE_50x50c.jpg",
            "https://images.craigslist.org/00w0w_3Xq0oTr3SyM_0uY0kE_50x50c.jpg",
            "https://images.craigslist.org/00a0a_gaaZyfPXYYB_0uY0kE_50x50c.jpg",
            "https://images.craigslist.org/01717_cznnYV5z57O_0uY0kE_50x50c.jpg",
            "https://images.craigslist.org/00r0r_4t1njqriMZi_0uY0kE_50x50c.jpg",
            "https://images.craigslist.org/00I0I_dYbYEpU3q7U_0uY0kE_50x50c.jpg",
            "https://images.craigslist.org/00i0i_l8oDhL7WRms_0uY0kE_50x50c.jpg",
            "https://images.craigslist.org/01515_dGzS5M8uTWk_0uY0kE_50x50c.jpg",
            "https://images.craigslist.org/00j0j_3gR9lTj58Zv_0uY0kE_50x50c.jpg",
            "https://images.craigslist.org/00p0p_6o1bzFw8mXC_0uY0kE_50x50c.jpg",
            "https://images.craigslist.org/00W0W_1eN4oLgf0gr_0uY0uY_50x50c.jpg"
          ],
          "image_dir": "472f1e66-7e38-4915-b12a-521f5e10cb5c"
        }
      }
    }
  ]
}